magictables/__init__.py
magictables/docs/api_reference.md
magictables/docs/quickstart.md
magictables/magictable.py
magictables/magictablechain.py
magictables/notsomagictable.py
magictables/prompts.py
magictables/sources.py
magictables/tablegraph.py
magictables/utils.py
magictables-1.1.3.dist-info/LICENSE
magictables-1.1.3.dist-info/METADATA
magictables-1.1.3.dist-info/WHEEL
magictables-1.1.3.dist-info/RECORD
