Metadata-Version: 2.1
Name: magictables
Version: 1.1.3
Summary: An advanced Python library designed to streamline data preparation and exploration for data scientists
License: GPL-3.0
Author: Lewis
Author-email: lewis@magictables.org
Requires-Python: >=3.10
Classifier: License :: OSI Approved :: GNU General Public License v3 (GPLv3)
Classifier: Programming Language :: Python :: 3
Classifier: Programming Language :: Python :: 3.10
Classifier: Programming Language :: Python :: 3.11
Requires-Dist: aiofiles (>=24.1.0,<25.0.0)
Requires-Dist: bs4 (>=0.0.2,<0.0.3)
Requires-Dist: dateparser (>=1.2.0,<2.0.0)
Requires-Dist: dill (>=0.3.8,<0.4.0)
Requires-Dist: litellm (>=1.41.25,<2.0.0)
Requires-Dist: neo4j (>=5.22.0,<6.0.0)
Requires-Dist: networkx (>=3.3,<4.0)
Requires-Dist: pandas (>=2.2.2,<3.0.0)
Requires-Dist: polars (>=1.2.1,<2.0.0)
Requires-Dist: py2neo (>=2021.2.4,<2022.0.0)
Requires-Dist: pyarrow (>=17.0.0,<18.0.0)
Requires-Dist: pypdf2 (>=3.0.1,<4.0.0)
Requires-Dist: python-dotenv (>=1.0.1,<2.0.0)
Requires-Dist: requests (>=2.32.3,<3.0.0)
Requires-Dist: scikit-learn (>=1.5.1,<2.0.0)
Requires-Dist: spycy-aneeshdurg (>=0.0.3,<0.0.4)
